pepflex-0.0.4.dist-info/licenses/LICENSE
pepflex_lib/__init__.py
pepflex-0.0.4.dist-info/METADATA
pepflex-0.0.4.dist-info/WHEEL
pepflex-0.0.4.dist-info/top_level.txt
pepflex-0.0.4.dist-info/RECORD
