Metadata-Version: 2.4
Name: pepflex
Version: 0.0.4
Summary: A modular framework for in silico peptide screening and evolution.
Author-email: Kyllian de Vos <kdevospro@gmail.com>
License: MIT
Project-URL: Homepage, https://github.com/Kdevos12/PepFlex/
Project-URL: Bug Tracker, https://github.com/Kdevos12/PepFlex/issues
Keywords: peptide,screening,evolution,bioinformatics,chemistry,rdkit
Classifier: Programming Language :: Python :: 3
Classifier: License :: OSI Approved :: MIT License
Classifier: Operating System :: OS Independent
Classifier: Topic :: Scientific/Engineering :: Chemistry
Classifier: Topic :: Scientific/Engineering :: Bio-Informatics
Classifier: Development Status :: 3 - Alpha
Requires-Python: >=3.8
License-File: LICENSE
Requires-Dist: pandas>=2.2.2
Requires-Dist: numpy>=2.0.2
Requires-Dist: rdkit>=2024.3.6
Provides-Extra: dev
Requires-Dist: pytest; extra == "dev"
Requires-Dist: twine; extra == "dev"
Requires-Dist: build; extra == "dev"
Dynamic: license-file
